[
    {
        "code": 1,
        "name": "Chickenjoy",
        "stock": 10,
        "price": 89
    },
    {
        "code": 2,
        "name": "Chickenjoy w/ Spaghetti",
        "stock": 32,
        "price": 100
    },
    {
        "code": 3,
        "name": "Chickenjoy w/ Fries",
        "stock": 70,
        "price": 96
    },
    {
        "code": 4,
        "name": "Burgersteak",
        "stock": 88,
        "price": 90
    },
    {
        "code": 5,
        "name": "Burgersteak w/ Lumpia",
        "stock": 25,
        "price": 110
    },
    {
        "code": 6,
        "name": "Burgersteak w/ Fries",
        "stock": 33,
        "price": 100
    },
    {
        "code": 7,
        "name": "Yumburger",
        "stock": 70,
        "price": 20
    },
    {
        "code": 8,
        "name": "Yumburger w/ Fries",
        "stock": 52,
        "price": 50
    },
    {
        "code": 9,
        "name": "Spaghetti",
        "stock": 7,
        "price": 60
    },
    {
        "code": 10,
        "name": "Spaghetti w/ Fries",
        "price": 80,
        "stock": 5
    },
    {
        "code": 11,
        "name": "Soft Drink",
        "stock": 26,
        "price": 150
    },
    {
        "code": 12,
        "name": "tea",
        "stock": 2,
        "price": 50
    }
]